wincrypto/__init__.py
wincrypto/algorithms.py
wincrypto/api.py
wincrypto/constants.py
wincrypto/native.py
wincrypto/util.py
wincrypto-0.3.dist-info/LICENSE
wincrypto-0.3.dist-info/METADATA
wincrypto-0.3.dist-info/WHEEL
wincrypto-0.3.dist-info/top_level.txt
wincrypto-0.3.dist-info/RECORD
