Metadata-Version: 2.1
Name: wincrypto
Version: 0.3
Summary: Windows Crypto API compatible decryption/encryption
Home-page: http://github.com/crappycrypto/wincrypto
Author: crappycrypto
Author-email: crappycrypto@xs4all.nl
License: MIT
Platform: UNKNOWN
Classifier: Development Status :: 3 - Alpha
Classifier: Topic :: Security :: Cryptography
Classifier: License :: OSI Approved :: MIT License
Classifier: Programming Language :: Python :: 2.7
Classifier: Programming Language :: Python :: 3.5
Classifier: Programming Language :: Python :: 3.6
Classifier: Programming Language :: Python :: 3.7
Classifier: Programming Language :: Python :: 3.8
Requires-Dist: pycryptodome
